llm_neuralwatt.py
llm_neuralwatt-0.0.4.dist-info/licenses/LICENSE
llm_neuralwatt-0.0.4.dist-info/METADATA
llm_neuralwatt-0.0.4.dist-info/WHEEL
llm_neuralwatt-0.0.4.dist-info/entry_points.txt
llm_neuralwatt-0.0.4.dist-info/top_level.txt
llm_neuralwatt-0.0.4.dist-info/RECORD
