Metadata-Version: 2.4
Name: llm-neuralwatt
Version: 0.0.4
Summary: A plugin to add support for the Neuralwatt AI inference service to llm
Author: Chris Adams
License-Expression: Apache-2.0
Project-URL: Homepage, https://github.com/mrchrisadams/llm-neuralwatt
Project-URL: Changelog, https://github.com/mrchrisadams/llm-neuralwatt/releases
Project-URL: Issues, https://github.com/mrchrisadams/llm-neuralwatt/issues
Project-URL: CI, https://github.com/mrchrisadams/llm-neuralwatt/actions
Requires-Python: >=3.10
License-File: LICENSE
Requires-Dist: llm
Provides-Extra: test
Requires-Dist: pytest; extra == "test"
Dynamic: license-file
